renovosolutions_elbv2_redirect/__init__.py
renovosolutions_elbv2_redirect/py.typed
renovosolutions_elbv2_redirect/_jsii/__init__.py
renovosolutions_elbv2_redirect/_jsii/cdk-library-elbv2-redirect@0.0.270.jsii.tgz
renovosolutions.aws_cdk_elbv2_redirect-0.0.270.dist-info/LICENSE
renovosolutions.aws_cdk_elbv2_redirect-0.0.270.dist-info/METADATA
renovosolutions.aws_cdk_elbv2_redirect-0.0.270.dist-info/WHEEL
renovosolutions.aws_cdk_elbv2_redirect-0.0.270.dist-info/top_level.txt
renovosolutions.aws_cdk_elbv2_redirect-0.0.270.dist-info/RECORD
